water/__init__.py
water/config.py
water/context.py
water/exceptions.py
water/execution_engine.py
water/flow.py
water/server.py
water/task.py
water/types.py
water_ai-0.1.0.dist-info/licenses/LICENSE
water_ai-0.1.0.dist-info/METADATA
water_ai-0.1.0.dist-info/WHEEL
water_ai-0.1.0.dist-info/top_level.txt
water_ai-0.1.0.dist-info/RECORD
