Metadata-Version: 2.4
Name: water-ai
Version: 0.1.0
Summary: A multi-agent orchestration framework that works with any agent framework
Author-email: Manthan Gupta <manthangupta109@gmail.com>
Project-URL: Homepage, https://github.com/manthanguptaa/water
Project-URL: Repository, https://github.com/manthanguptaa/water
Keywords: water-ai,multi-agent,orchestration,llm,large-language-model,framework,agents,ai-agents,workflow,pipeline,langchain,crewai,agno,autogen,distributed,async,coordination,agent-framework,multi-agent-systems
Classifier: Development Status :: 4 - Beta
Classifier: Intended Audience :: Developers
Classifier: Intended Audience :: Science/Research
Classifier: License :: OSI Approved :: Apache Software License
Classifier: Operating System :: OS Independent
Classifier: Programming Language :: Python :: 3
Classifier: Programming Language :: Python :: 3.8
Classifier: Programming Language :: Python :: 3.9
Classifier: Programming Language :: Python :: 3.10
Classifier: Programming Language :: Python :: 3.11
Classifier: Programming Language :: Python :: 3.12
Classifier: Topic :: Scientific/Engineering :: Artificial Intelligence
Classifier: Topic :: Software Development :: Libraries :: Python Modules
Classifier: Topic :: System :: Distributed Computing
Classifier: Framework :: FastAPI
Classifier: Framework :: AsyncIO
Requires-Python: >=3.8
License-File: LICENSE
Requires-Dist: pydantic>=2.0.0
Requires-Dist: fastapi>=0.104.0
Requires-Dist: uvicorn[standard]>=0.24.0
Provides-Extra: dev
Requires-Dist: pytest>=7.0.0; extra == "dev"
Requires-Dist: pytest-asyncio>=0.21.0; extra == "dev"
Dynamic: license-file
